datarepr/__init__.py
datarepr/core.py
datarepr/tests/__init__.py
datarepr/tests/test_0.py
datarepr-1.1.0.dist-info/licenses/LICENSE.txt
datarepr-1.1.0.dist-info/METADATA
datarepr-1.1.0.dist-info/WHEEL
datarepr-1.1.0.dist-info/top_level.txt
datarepr-1.1.0.dist-info/RECORD
