Metadata-Version: 2.4
Name: datarepr
Version: 1.1.0
Summary: This project allows for common sense data representation.
Author-email: Johannes <johannes.programming@gmail.com>
License: The MIT License (MIT)
Project-URL: Download, https://pypi.org/project/datarepr/#files
Project-URL: Index, https://pypi.org/project/datarepr/
Project-URL: Source, https://github.com/johannes-programming/datarepr/
Project-URL: Website, https://datarepr.johannes-programming.online/
Classifier: Development Status :: 5 - Production/Stable
Classifier: Intended Audience :: Developers
Classifier: License :: OSI Approved :: MIT License
Classifier: Natural Language :: English
Classifier: Operating System :: OS Independent
Classifier: Programming Language :: Python
Classifier: Programming Language :: Python :: 3
Classifier: Programming Language :: Python :: 3 :: Only
Classifier: Typing :: Typed
Requires-Python: >=3.11
License-File: LICENSE.txt
Dynamic: license-file
